mal_simulator-1.1.2.dist-info/licenses/AUTHORS
mal_simulator-1.1.2.dist-info/licenses/LICENSE
malsim/__init__.py
malsim/__main__.py
malsim/graph_processing.py
malsim/mal_simulator.py
malsim/scenario.py
malsim/ttc_utils.py
malsim/agents/__init__.py
malsim/agents/decision_agent.py
malsim/agents/keyboard_input.py
malsim/agents/passive_agent.py
malsim/agents/random_agent.py
malsim/agents/attackers/__init__.py
malsim/agents/attackers/searchers.py
malsim/agents/attackers/shortest_path.py
malsim/agents/attackers/ttc_soft_min.py
malsim/agents/defenders/__init__.py
malsim/agents/defenders/heuristic_agent.py
malsim/agents/utils/path_finding.py
malsim/envs/__init__.py
malsim/envs/base_classes.py
malsim/envs/gym_envs.py
malsim/envs/malsim_vectorized_obs_env.py
malsim/visualization/malsim_gui_client.py
mal_simulator-1.1.2.dist-info/METADATA
mal_simulator-1.1.2.dist-info/WHEEL
mal_simulator-1.1.2.dist-info/entry_points.txt
mal_simulator-1.1.2.dist-info/top_level.txt
mal_simulator-1.1.2.dist-info/RECORD
