Metadata-Version: 2.4
Name: mal-simulator
Version: 1.1.2
Summary: A MAL compliant simulator.
Author-email: Andrei Buhaiu <buhaiu@kth.se>, Joakim Loxdal <loxdal@kth.se>, Jakob Nyberg <jaknyb@kth.se>, Nikolaos Kakouros <nkak@kth.se>, Sandor Berglund <sandorb@kth.se>
License: Apache Software License
Project-URL: Homepage, https://github.com/mal-lang/mal-simulator
Project-URL: Bug Tracker, https://github.com/mal-lang/mal-simulator/issues
Project-URL: Repository, https://github.com/mal-lang/mal-simulator
Keywords: mal
Classifier: Development Status :: 3 - Alpha
Classifier: Intended Audience :: Science/Research
Classifier: Programming Language :: Python :: 3
Classifier: License :: OSI Approved :: Apache Software License
Classifier: Operating System :: OS Independent
Classifier: Topic :: Scientific/Engineering
Requires-Python: >=3.10
License-File: LICENSE
License-File: AUTHORS
Requires-Dist: mal-toolbox<2.0.0,>=1.1.0
Requires-Dist: PyYAML>=6.0.1
Requires-Dist: numpy>=1.21.4
Requires-Dist: scipy
Requires-Dist: networkx
Requires-Dist: requests
Provides-Extra: ml
Requires-Dist: pettingzoo>=1.24.2; extra == "ml"
Requires-Dist: gymnasium~=1.0; extra == "ml"
Provides-Extra: dev
Requires-Dist: pytest; extra == "dev"
Requires-Dist: mypy; extra == "dev"
Requires-Dist: ruff; extra == "dev"
Dynamic: license-file
